docrawl/__init__.py
docrawl/docrawl_client.py
docrawl/docrawl_core.py
docrawl/docrawl_launcher.py
docrawl/docrawl_logger.py
docrawl/elements.py
docrawl/errors.py
docrawl/utils.py
docrawl-1.4.1.dist-info/LICENSE
docrawl-1.4.1.dist-info/METADATA
docrawl-1.4.1.dist-info/WHEEL
docrawl-1.4.1.dist-info/top_level.txt
docrawl-1.4.1.dist-info/RECORD
